Workbook

Sheet Sheet 1
A1: codpr | B1: recherche_v v | C1: poste_depense
A2: Riz local brisé | B2: =VLOOKUP(A2,Feuil1!$A$1:$B$523,2,FALSE) -> Cereales | C2: Cereales
A3: Riz local entier | B3: =VLOOKUP(A3,Feuil1!$A$1:$B$523,2,FALSE) -> Cereales | C3: Cereales
A4: Riz importé brisé | B4: =VLOOKUP(A4,Feuil1!$A$1:$B$523,2,FALSE) -> Cereales | C4: Cereales
A5: Riz importé entier | B5: =VLOOKUP(A5,Feuil1!$A$1:$B$523,2,FALSE) -> Cereales | C5: Cereales
A6: Maïs en épi | B6: =VLOOKUP(A6,Feuil1!$A$1:$B$523,2,FALSE) -> Cereales | C6: Cereales
A7: Maïs en grain | B7: =VLOOKUP(A7,Feuil1!$A$1:$B$523,2,FALSE) -> Cereales | C7: Cereales
A8: Mil | B8: =VLOOKUP(A8,Feuil1!$A$1:$B$523,2,FALSE) -> Cereales | C8: Cereales
A9: Sorgho | B9: =VLOOKUP(A9,Feuil1!$A$1:$B$523,2,FALSE) -> Cereales | C9: Cereales
A10: Blé | B10: =VLOOKUP(A10,Feuil1!$A$1:$B$523,2,FALSE) -> Cereales | C10: Cereales
A11: Fonio | B11: =VLOOKUP(A11,Feuil1!$A$1:$B$523,2,FALSE) -> Cereales | C11: Cereales
A12: Autres céréales | B12: =VLOOKUP(A12,Feuil1!$A$1:$B$523,2,FALSE) -> Cereales | C12: Cereales
A13: Farine de maïs | B13: =VLOOKUP(A13,Feuil1!$A$1:$B$523,2,FALSE) -> Cereales | C13: Cereales
... A440: Location salle/chaise funér./autres | B440: =VLOOKUP(A440,Feuil1!$A$1:$B$523,2,FALSE) -> Ceremonies_autres | C440: Ceremonies_autres

Sheet Feuil1
A1: Abats blancs (pieds, tête, etc.) et tripes (estomac, intestins, etc.) | B1: Viandes
A2: Bières et vins traditionnels (dolo, vin de palme, vin de raphia, vin de cajou, etc.) | B2: Alcool_tabac
A3: Bières industrielles | B3: Alcool_tabac
A4: Cigarettes, Tabac | B4: Alcool_tabac
A5: Cigarettes, Tabac | B5: Alcool_tabac
A6: Vins modernes | B6: Alcool_tabac
A7: Whisky et autres liqueurs | B7: Alcool_tabac
A8: Autres effets personnels: valise, sac de voyage, sac à main, perruques, chapeau, lunettes solaires, parapluies, parasol, canne, porte-monnaie, portefeuille, articles pour fumeurs, articles pour bébé, articles funéraires | B8: Autres
A9: Autres services: annonce à la radio, dans un journal/à la télévision, pompe funèbre | B9: Autres
A10: Boucle d'oreilles, colliers, bracelets, bijoux, autres articles de bijouterie et joaillerie n.d.a | B10: Autres
A11: Frais d'assurance d'un moyen de transport individuel (auto, moto, etc.), assurance de voyage | B11: Autres
A12: Frais d'assurance d'une maison ou tout autre bien qu'un moyen de transport | B12: Autres
... A523: Autres effets personnels: valise, sac de voyage, sac à main, perruques, chapeau, lunettes solaires, parapluies, parasol, canne, porte-monnaie,portefeuille, articles pour fumeurs articles pour bébé , articles funéraires | B523: Autres
